zensols/bibstract/resources/app.conf
zensols/bibstract/resources/converters.conf
zensols/bibstract/resources/default.conf
zensols/bibstract/resources/obj.conf
zensols/bibstract/__init__.py
zensols/bibstract/app.py
zensols/bibstract/cli.py
zensols/bibstract/converter.py
zensols/bibstract/domain.py
zensols/bibstract/extractor.py
zensols/bibstract/pkg.py
zensols_bibstract-1.5.0.dist-info/METADATA
zensols_bibstract-1.5.0.dist-info/WHEEL
zensols_bibstract-1.5.0.dist-info/entry_points.txt
zensols_bibstract-1.5.0.dist-info/licenses/LICENSE.md
zensols_bibstract-1.5.0.dist-info/RECORD
