Metadata-Version: 2.3
Name: zensols_bibstract
Version: 1.5.0
Summary: This utility extracts Biblatex references from a Latex.
Project-URL: Homepage, https://github.com/plandes/bibstract
Project-URL: Documentation, https://plandes.github.io/bibstract
Project-URL: Repository, https://github.com/plandes/bibstract.git
Project-URL: Issues, https://github.com/plandes/bibstract/issues
Project-URL: Changelog, https://github.com/plandes/bibstract/blob/master/CHANGELOG.md
Author-email: Paul Landes <landes@mailc.net>
License: MIT
Keywords: bibtex,latex
Requires-Python: <3.15,>=3.11
Requires-Dist: bibtexparser==1.4.3
Requires-Dist: dateparser~=1.2.2
Requires-Dist: zensols-util~=1.16.2
